eve_sqlalchemy/__about__.py
eve_sqlalchemy/__init__.py
eve_sqlalchemy/media.py
eve_sqlalchemy/parser.py
eve_sqlalchemy/structures.py
eve_sqlalchemy/utils.py
eve_sqlalchemy/validation.py
eve_sqlalchemy/config/__init__.py
eve_sqlalchemy/config/domainconfig.py
eve_sqlalchemy/config/fieldconfig.py
eve_sqlalchemy/config/resourceconfig.py
eve_sqlalchemy/examples/__init__.py
eve_sqlalchemy/examples/auth/__init__.py
eve_sqlalchemy/examples/foreign_primary_key/__init__.py
eve_sqlalchemy/examples/foreign_primary_key/app.py
eve_sqlalchemy/examples/foreign_primary_key/domain.py
eve_sqlalchemy/examples/foreign_primary_key/settings.py
eve_sqlalchemy/examples/many_to_many/__init__.py
eve_sqlalchemy/examples/many_to_many/app.py
eve_sqlalchemy/examples/many_to_many/domain.py
eve_sqlalchemy/examples/many_to_many/settings.py
eve_sqlalchemy/examples/many_to_one/__init__.py
eve_sqlalchemy/examples/many_to_one/app.py
eve_sqlalchemy/examples/many_to_one/domain.py
eve_sqlalchemy/examples/many_to_one/settings.py
eve_sqlalchemy/examples/one_to_many/__init__.py
eve_sqlalchemy/examples/one_to_many/app.py
eve_sqlalchemy/examples/one_to_many/domain.py
eve_sqlalchemy/examples/one_to_many/settings.py
eve_sqlalchemy/examples/simple/__init__.py
eve_sqlalchemy/examples/simple/app.py
eve_sqlalchemy/examples/simple/example_data.py
eve_sqlalchemy/examples/simple/settings.py
eve_sqlalchemy/examples/simple/tables.py
eve_sqlalchemy/examples/trivial/__init__.py
eve_sqlalchemy/examples/trivial/trivial.py
eve_sqlalchemy/tests/__init__.py
eve_sqlalchemy/tests/delete.py
eve_sqlalchemy/tests/get.py
eve_sqlalchemy/tests/patch.py
eve_sqlalchemy/tests/post.py
eve_sqlalchemy/tests/put.py
eve_sqlalchemy/tests/sql.py
eve_sqlalchemy/tests/test_settings.py
eve_sqlalchemy/tests/test_sql_tables.py
eve_sqlalchemy/tests/test_validation.py
eve_sqlalchemy/tests/utils.py
eve_sqlalchemy/tests/config/__init__.py
eve_sqlalchemy/tests/config/domainconfig/__init__.py
eve_sqlalchemy/tests/config/domainconfig/ambiguous_relations.py
Eve_SQLAlchemy-0.7.1.dist-info/AUTHORS
Eve_SQLAlchemy-0.7.1.dist-info/LICENSE
Eve_SQLAlchemy-0.7.1.dist-info/METADATA
Eve_SQLAlchemy-0.7.1.dist-info/WHEEL
Eve_SQLAlchemy-0.7.1.dist-info/top_level.txt
Eve_SQLAlchemy-0.7.1.dist-info/zip-safe
Eve_SQLAlchemy-0.7.1.dist-info/RECORD
