Metadata-Version: 2.1
Name: Eve-SQLAlchemy
Version: 0.7.1
Summary: REST API framework powered by Eve, SQLAlchemy and good intentions.
Home-page: https://github.com/pyeve/eve-sqlalchemy
Author: Dominik Kellner
Author-email: dkellner@dkellner.de
License: BSD
Keywords: flask sqlalchemy rest
Platform: any
Classifier: Development Status :: 4 - Beta
Classifier: Environment :: Web Environment
Classifier: Intended Audience :: Developers
Classifier: License :: OSI Approved :: BSD License
Classifier: Operating System :: OS Independent
Classifier: Programming Language :: Python
Classifier: Programming Language :: Python :: 2
Classifier: Programming Language :: Python :: 2.7
Classifier: Programming Language :: Python :: 3
Classifier: Programming Language :: Python :: 3.4
Classifier: Programming Language :: Python :: 3.5
Classifier: Programming Language :: Python :: 3.6
Classifier: Programming Language :: Python :: 3.7
Classifier: Programming Language :: Python :: Implementation :: CPython
Classifier: Programming Language :: Python :: Implementation :: PyPy
Classifier: Topic :: Internet :: WWW/HTTP :: Dynamic Content
Requires-Dist: Eve (<0.8)
Requires-Dist: Flask-SQLAlchemy (<2.999,>=2.4)
Requires-Dist: SQLAlchemy (>=1.3)
Provides-Extra: test
Requires-Dist: mock ; extra == 'test'
Requires-Dist: pytest ; extra == 'test'
